xf_aes_gcm/VERSION
xf_aes_gcm/__init__.py
xf_aes_gcm/aesgcm.py
xf_aes_gcm-1.0.0.dist-info/LICENSE
xf_aes_gcm-1.0.0.dist-info/METADATA
xf_aes_gcm-1.0.0.dist-info/WHEEL
xf_aes_gcm-1.0.0.dist-info/entry_points.txt
xf_aes_gcm-1.0.0.dist-info/top_level.txt
xf_aes_gcm-1.0.0.dist-info/RECORD
