Metadata-Version: 2.1
Name: xf-aes-gcm
Version: 1.0.0
Summary: A general AES-GCM en-/decryption utility with support for additional data (AEAD) and tweaks to work with the passwords encrypted by S&P Global's Xpressfeed applications, which use this algorithm
Home-page: https://github.com/richmilne/xf-aes-gcm/releases/tag/v1.0.0
Author: Richard Milne
Author-email: richmilne@hotmail.com
License: GPLv3
Platform: UNKNOWN
Classifier: Development Status :: 4 - Beta
Classifier: Environment :: Console
Classifier: License :: OSI Approved :: GNU General Public License v3 (GPLv3)
Classifier: Operating System :: POSIX
Classifier: Programming Language :: Python :: 3
Requires-Dist: cryptography
